setup.py
distributions_dav/Binomialdistribution.py
distributions_dav/Gaussiandistribution.py
distributions_dav/Generaldistribution.py
distributions_dav/__init__.py
distributions_dav.egg-info/PKG-INFO
distributions_dav.egg-info/SOURCES.txt
distributions_dav.egg-info/dependency_links.txt
distributions_dav.egg-info/not-zip-safe
distributions_dav.egg-info/top_level.txt