Metadata-Version: 1.0
Name: distributions-dav
Version: 0.1
Summary: Gaussian and Binomial distributions
Home-page: UNKNOWN
Author: David Vindas
Author-email: isdavid506@gmail.com
License: UNKNOWN
Platform: UNKNOWN
